evo2/__init__.py
evo2/models.py
evo2/scoring.py
evo2/utils.py
evo2/version.py
evo2/configs/evo2-1b-8k.yml
evo2/configs/evo2-40b-1m.yml
evo2/configs/evo2-40b-8k.yml
evo2/configs/evo2-7b-1m.yml
evo2/configs/evo2-7b-262k.yml
evo2/configs/evo2-7b-8k.yml
evo2/configs/shc-evo2-7b-8k-2T-v2-interleave.yml
evo2/test/__init__.py
evo2/test/test_evo2.py
evo2/test/test_evo2_generation.py
evo2/test/test_model_load.py
evo2/test/data/__init__.py
evo2/test/data/prompts.csv
evo2-0.4.0.dist-info/licenses/AUTHORS
evo2-0.4.0.dist-info/licenses/LICENSE
evo2-0.4.0.dist-info/licenses/NOTICE
evo2-0.4.0.dist-info/METADATA
evo2-0.4.0.dist-info/WHEEL
evo2-0.4.0.dist-info/top_level.txt
evo2-0.4.0.dist-info/RECORD
