Metadata-Version: 2.4
Name: evo2
Version: 0.4.0
Summary: Genome modeling across all domains of life
Author: Evo 2 Team
License:                              Apache License
Project-URL: Homepage, https://github.com/arcinstitute/evo2
Project-URL: Repository, https://github.com/arcinstitute/evo2
Requires-Python: <3.13,>=3.11
License-File: LICENSE
License-File: NOTICE
License-File: AUTHORS
Requires-Dist: biopython
Requires-Dist: huggingface_hub
Requires-Dist: torch
Requires-Dist: vtx>=0.0.8
Dynamic: license-file
